citation_url/__init__.py
citation_url/endnote.py
citation_url/py.typed
citation_url/version.py
citation_url/zotero.py
citation_url-0.1.1.dist-info/LICENSE
citation_url-0.1.1.dist-info/METADATA
citation_url-0.1.1.dist-info/WHEEL
citation_url-0.1.1.dist-info/top_level.txt
citation_url-0.1.1.dist-info/RECORD
