Metadata-Version: 2.1
Name: citation-url
Version: 0.1.1
Summary: Parse URLs for DOIs, PubMed identifiers, PMC identifiers, arXiv identifiers, etc.
Home-page: https://github.com/cthoyt/citation-url
Download-URL: https://github.com/cthoyt/citation-url/releases
Author: Charles Tapley Hoyt
Author-email: cthoyt@gmail.com
Maintainer: Charles Tapley Hoyt
Maintainer-email: cthoyt@gmail.com
License: MIT
Project-URL: Bug Tracker, https://github.com/cthoyt/citation-url/issues
Project-URL: Source Code, https://github.com/cthoyt/citation-url
Keywords: snekpack,cookiecutter
Platform: UNKNOWN
Classifier: Development Status :: 1 - Planning
Classifier: Environment :: Console
Classifier: Intended Audience :: Developers
Classifier: License :: OSI Approved :: MIT License
Classifier: Operating System :: OS Independent
Classifier: Framework :: Pytest
Classifier: Framework :: tox
Classifier: Framework :: Sphinx
Classifier: Programming Language :: Python
Classifier: Programming Language :: Python :: 3.6
Classifier: Programming Language :: Python :: 3.7
Classifier: Programming Language :: Python :: 3.8
Classifier: Programming Language :: Python :: 3.9
Classifier: Programming Language :: Python :: 3.10
Classifier: Programming Language :: Python :: 3 :: Only
Requires-Python: >=3.6
License-File: LICENSE
Provides-Extra: docs
Requires-Dist: sphinx ; extra == 'docs'
Requires-Dist: sphinx-rtd-theme ; extra == 'docs'
Requires-Dist: sphinx-autodoc-typehints ; extra == 'docs'
Provides-Extra: endnote
Requires-Dist: tqdm ; extra == 'endnote'
Requires-Dist: click ; extra == 'endnote'
Requires-Dist: defusedxml ; extra == 'endnote'
Requires-Dist: pystow ; extra == 'endnote'
Requires-Dist: wikidataintegrator ; extra == 'endnote'
Provides-Extra: tests
Requires-Dist: pytest ; extra == 'tests'
Requires-Dist: coverage ; extra == 'tests'
